sparse_numba/__init__.py
sparse_numba/benchmark_parallel_slu.py
sparse_numba/benchmark_parallel_umf.py
sparse_numba/benchmark_single_slu.py
sparse_numba/benchmark_single_umf.py
sparse_numba/test_import.py
sparse_numba/conversion/__init__.py
sparse_numba/conversion/matrix_conversion_numba.py
sparse_numba/sparse_superlu/cy_superlu_wrapper.cp38-win_amd64.pyd
sparse_numba/sparse_superlu/cy_superlu_wrapper.pyx
sparse_numba/sparse_superlu/superlu_numba_interface.py
sparse_numba/sparse_superlu/superlu_wrapper.c
sparse_numba/sparse_superlu/test/test_example_slu.py
sparse_numba/sparse_superlu/test/test_superlu_installation.py
sparse_numba/sparse_umfpack/cy_umfpack_wrapper.cp38-win_amd64.pyd
sparse_numba/sparse_umfpack/cy_umfpack_wrapper.pyx
sparse_numba/sparse_umfpack/umfpack_numba_interface.py
sparse_numba/sparse_umfpack/umfpack_wrapper.c
sparse_numba/sparse_umfpack/test/test_coo_csc_conversion.py
sparse_numba/sparse_umfpack/test/test_example_umfpack.py
sparse_numba/vendor/openblas/bin/libopenblas.dll
sparse_numba/vendor/superlu/bin/libgcc_s_seh-1.dll
sparse_numba/vendor/superlu/bin/libgfortran-5.dll
sparse_numba/vendor/superlu/bin/libgomp-1.dll
sparse_numba/vendor/superlu/bin/libquadmath-0.dll
sparse_numba/vendor/superlu/bin/libsuperlu-7.dll
sparse_numba/vendor/superlu/bin/libsuperlu_fortran-7.dll
sparse_numba/vendor/superlu/bin/libwinpthread-1.dll
sparse_numba-0.1.10.dist-info/LICENSE
sparse_numba-0.1.10.dist-info/METADATA
sparse_numba-0.1.10.dist-info/WHEEL
sparse_numba-0.1.10.dist-info/top_level.txt
sparse_numba-0.1.10.dist-info/RECORD
