Metadata-Version: 2.1
Name: sparse_numba
Version: 0.1.10
Summary: Customized sparse solver with Numba support
Home-page: https://github.com/th1275/sparse_numba
Author: Tianqi Hong
Author-email: tianqi.hong@uga.edu
Classifier: Programming Language :: Python :: 3
Classifier: License :: OSI Approved :: BSD License
Classifier: Operating System :: Microsoft :: Windows
Classifier: Operating System :: POSIX :: Linux
Classifier: Operating System :: MacOS :: MacOS X
Requires-Python: >=3.8
License-File: LICENSE
Requires-Dist: numpy>=1.13.3
Requires-Dist: numba>=0.58.0
